tsql/__init__.py
tsql/py.typed
tsql_py-0.0.0b1.dist-info/METADATA
tsql_py-0.0.0b1.dist-info/WHEEL
tsql_py-0.0.0b1.dist-info/licenses/LICENSE
tsql_py-0.0.0b1.dist-info/RECORD
