Metadata-Version: 2.4
Name: tsql-py
Version: 0.0.0b1
Summary: Templated SQL (A templating engine for SQL)
License: GPL-3.0
License-File: LICENSE
Keywords: sql,templating,database,query
Author: Arne K. (TRC-Loop)
Author-email: me@arne.sh
Requires-Python: >=3.9,<4.0
Classifier: Development Status :: 2 - Pre-Alpha
Classifier: Intended Audience :: Developers
Classifier: License :: OSI Approved :: GNU General Public License v3 (GPLv3)
Classifier: Programming Language :: Python :: 3
Classifier: Programming Language :: Python :: 3 :: Only
Classifier: Programming Language :: Python :: 3.9
Classifier: Programming Language :: Python :: 3.10
Classifier: Programming Language :: Python :: 3.11
Classifier: Programming Language :: Python :: 3.12
Classifier: Topic :: Database
Classifier: Topic :: Software Development :: Libraries
Project-URL: Homepage, https://go.gmrze.com/tsql
Project-URL: Issues, https://github.com/gmrze/tSQL/issues
Project-URL: Repository, https://github.com/gmrze/tSQL
